{
  "nom": "McDavid 195 protège-cheville basket",
  "description": "Le McDavid 195 est une protège-cheville de référence conçue pour offrir un soutien optimal et une stabilité renforcée lors de vos matchs et entraînements de basket. Sa construction anatomique et ses matériaux respirants garantissent un maintien fiable tout en préservant votre mobilité.",
  "categorie": "Accessoires",
  "badge": null,
  "lien_amazon": "https://www.amazon.fr/s?k=McDavid%20195%20prot%C3%A8ge-cheville%20basket&tag=sportguidefr-21",
  "lien_article": "/articles/meilleur-protege-cheville-de-basket-2026"
}